dishka_flet/__init__.py
dishka_flet/_consts.py
dishka_flet/_getters.py
dishka_flet/_injectors.py
dishka_flet/_version.py
dishka_flet/flet.py
dishka_flet/py.typed
dishka_flet-0.0.3.dist-info/METADATA
dishka_flet-0.0.3.dist-info/WHEEL
dishka_flet-0.0.3.dist-info/licenses/LICENSE
dishka_flet-0.0.3.dist-info/RECORD
