Metadata-Version: 2.4
Name: dishka-flet
Version: 0.0.3
Summary: Integration package for Dishka DI and Flet framework
Project-URL: Source, https://github.com/C3EQUALZz/dishka-flet
Project-URL: Homepage, https://github.com/C3EQUALZz/dishka-flet
Project-URL: Tracker, https://github.com/C3EQUALZz/dishka-flet/issues
Author-email: Danil Kovalev <dan.kovalev2013@gmail.com>
License-Expression: Apache-2.0
License-File: LICENSE
Classifier: Intended Audience :: Developers
Classifier: License :: OSI Approved :: Apache Software License
Classifier: Operating System :: OS Independent
Classifier: Programming Language :: Python :: 3.10
Classifier: Programming Language :: Python :: 3.11
Classifier: Programming Language :: Python :: 3.12
Classifier: Programming Language :: Python :: 3.13
Classifier: Programming Language :: Python :: 3.14
Classifier: Topic :: Software Development :: Libraries
Classifier: Typing :: Typed
Requires-Python: >=3.10
Requires-Dist: dishka<2,>=1.7
Requires-Dist: flet[all]>=0.28.3
